tintap/__init__.py
tintap/client.py
tintap/exceptions.py
tintap-0.1.1.dist-info/licenses/LICENSE
tintap-0.1.1.dist-info/METADATA
tintap-0.1.1.dist-info/WHEEL
tintap-0.1.1.dist-info/top_level.txt
tintap-0.1.1.dist-info/RECORD
