Metadata-Version: 2.4
Name: tintap
Version: 0.1.1
Summary: AI audio detection and attribution Python SDK for tintap platform
Home-page: https://github.com/tintap/tintap-python
Author: tintap
Author-email: tintap <contact@tintap.ai>
License: MIT
Project-URL: Homepage, https://tintap.ai
Project-URL: Documentation, https://docs.tintap.ai
Project-URL: Repository, https://github.com/tintap/tintap-python
Project-URL: Bug Tracker, https://github.com/tintap/tintap-python/issues
Keywords: ai,audio,detection,analysis,artificial-intelligence,audio-processing,content-attribution,machine-learning,music,speech
Classifier: Development Status :: 4 - Beta
Classifier: Intended Audience :: Developers
Classifier: Topic :: Software Development :: Libraries :: Python Modules
Classifier: Topic :: Multimedia :: Sound/Audio :: Analysis
Classifier: Topic :: Scientific/Engineering :: Artificial Intelligence
Classifier: License :: OSI Approved :: MIT License
Classifier: Programming Language :: Python :: 3
Classifier: Programming Language :: Python :: 3.7
Classifier: Programming Language :: Python :: 3.8
Classifier: Programming Language :: Python :: 3.9
Classifier: Programming Language :: Python :: 3.10
Classifier: Programming Language :: Python :: 3.11
Classifier: Programming Language :: Python :: 3.12
Classifier: Operating System :: OS Independent
Requires-Python: >=3.7
License-File: LICENSE
Requires-Dist: requests>=2.25.0
Requires-Dist: urllib3>=1.26.0
Provides-Extra: dev
Requires-Dist: pytest>=6.0; extra == "dev"
Requires-Dist: pytest-asyncio>=0.18.0; extra == "dev"
Requires-Dist: black>=22.0.0; extra == "dev"
Requires-Dist: flake8>=4.0.0; extra == "dev"
Requires-Dist: mypy>=0.900; extra == "dev"
Dynamic: author
Dynamic: home-page
Dynamic: license-file
Dynamic: requires-python
